cheapbot/__init__.py
cheapbot/cheapbot.py
cheapbot-0.0.1.dist-info/METADATA
cheapbot-0.0.1.dist-info/WHEEL
cheapbot-0.0.1.dist-info/entry_points.txt
cheapbot-0.0.1.dist-info/top_level.txt
cheapbot-0.0.1.dist-info/RECORD
