Metadata-Version: 2.1
Name: cheapbot
Version: 0.0.1
Summary: DNS Authenticator for Namecheap DNS
Home-page: https://github.com/ZiadMansourM/cheapbot
Author: Ziad Hassanin
Author-email: ziadmansour.4.9.2000@gmail.com
Requires-Dist: certbot
